awaitlist/__init__.py
awaitlist/awaitlist.py
awaitlist/py.typed
awaitlist-0.1.2.dist-info/METADATA
awaitlist-0.1.2.dist-info/WHEEL
awaitlist-0.1.2.dist-info/licenses/LICENSE
awaitlist-0.1.2.dist-info/RECORD
