Metadata-Version: 2.4
Name: awaitlist
Version: 0.1.2
Summary: A simple async task scheduler
Project-URL: Repository, https://github.com/KojiOchiai/awaitlist
Author-email: KojiOchiai <12869331+KojiOchiai@users.noreply.github.com>
License: MIT License
License-File: LICENSE
Requires-Python: >=3.10
